niffler/__init__.py
niffler/gold.py
niffler/niffler.py
niffler/sites/__init__.py
niffler/sites/erome.py
niffler/sites/giphdeliverynetwork.py
niffler/sites/giphycat.py
niffler/sites/imgur.py
niffler/sites/media.py
niffler/sites/reddit.py
niffler/sites/redgifs.py
niffler/sites/web.py
niffler/sites/youtube.py
tests/__init__.py
tests/niffler_tests.py
niffler-0.2.1.dist-info/LICENSE
niffler-0.2.1.dist-info/METADATA
niffler-0.2.1.dist-info/WHEEL
niffler-0.2.1.dist-info/entry_points.txt
niffler-0.2.1.dist-info/top_level.txt
niffler-0.2.1.dist-info/RECORD
