Metadata-Version: 2.1
Name: niffler
Version: 0.2.1
Summary: Dig up gold on the web
Home-page: UNKNOWN
License: UNKNOWN
Platform: UNKNOWN
Classifier: Programming Language :: Python :: 3
Classifier: License :: OSI Approved :: MIT License
Classifier: Operating System :: OS Independent
Requires-Python: >=3.6
Requires-Dist: requests
Requires-Dist: youtube-dl
Requires-Dist: bs4
Requires-Dist: lxml
Requires-Dist: ipython
